setup.py
rtlib/rtlib_cython.pyx
rtpipe/FDMT.py
rtpipe/RT.py
rtpipe/__init__.py
rtpipe/calpipe.py
rtpipe/cli.py
rtpipe/interactive.py
rtpipe/nbpipeline.py
rtpipe/parsecal.py
rtpipe/parsecands.py
rtpipe/parsems.py
rtpipe/parseparams.py
rtpipe/parsesdm.py
rtpipe/reproduce.py
rtpipe/rtlib_numba.py
rtpipe/test1.py
rtpipe/version.py
rtpipe.egg-info/PKG-INFO
rtpipe.egg-info/SOURCES.txt
rtpipe.egg-info/dependency_links.txt
rtpipe.egg-info/entry_points.txt
rtpipe.egg-info/not-zip-safe
rtpipe.egg-info/requires.txt
rtpipe.egg-info/top_level.txt