Metadata-Version: 1.0
Name: rtpipe
Version: 1.60
Summary: Python scripts for fast transient searches with radio interferometer data
Home-page: http://github.com/caseyjlaw/rtpipe
Author: Casey Law
Author-email: caseyjlaw@gmail.com
License: UNKNOWN
Platform: UNKNOWN
